rdkit_buildutils/__init__.py
rdkit_buildutils/core.py
rdkit_buildutils/datatypes.py
rdkit_buildutils/duplicates_pandas.py
rdkit_buildutils/filters.py
rdkit_buildutils/helm.py
rdkit_buildutils/logging_utils.py
rdkit_buildutils/matching.py
rdkit_buildutils/query_variants.py
rdkit_buildutils/rgd_assign.py
rdkit_buildutils/rgroup_core.py
rdkit_buildutils/rgroup_extract.py
rdkit_buildutils/scaffold_normalize.py
rdkit_buildutils/standardize.py
rdkit_buildutils/rgroup/__init__.py
rdkit_buildutils/rgroup/altcores.py
rdkit_buildutils-0.3.3.dist-info/licenses/LICENSE
rdkit_buildutils-0.3.3.dist-info/METADATA
rdkit_buildutils-0.3.3.dist-info/WHEEL
rdkit_buildutils-0.3.3.dist-info/top_level.txt
rdkit_buildutils-0.3.3.dist-info/RECORD
