Metadata-Version: 2.4
Name: rdkit_buildutils
Version: 0.3.3
Summary: RDKit utilities for placeholder conversion, query matching, R-group decomposition, scaffold normalization, and ALT core providers
Author: Fabio Nelli
License: MIT License
Project-URL: Homepage, https://github.com/nelli-datascience/rdkit_buildutils
Project-URL: Issues, https://github.com/nelli-datascience/rdkit_buildutils/issues
Project-URL: Changelog, https://github.com/nelli-datascience/rdkit_buildutils/blob/main/CHANGELOG.md
Requires-Python: >=3.8
License-File: LICENSE
Provides-Extra: pandas
Requires-Dist: pandas>=1.5; extra == "pandas"
Provides-Extra: db
Requires-Dist: sqlalchemy>=2.0; extra == "db"
Requires-Dist: psycopg2-binary>=2.9; extra == "db"
Provides-Extra: yaml
Requires-Dist: pyyaml>=6.0; extra == "yaml"
Dynamic: license-file
